flask_cli/__init__.py
flask_cli/__version__.py
flask_cli/cli/__init__.py
flask_cli/cli/main.py
flask_cli/common/__init__.py
flask_cli/create/__init__.py
flask_cli/create/cli.py
flask_cli/templates/__init__.py
flask_cli/templates/cli.py
flask_cli/templates/exception.py
flask_cli/templates/templates.py
flasky_cli-1.0.3.dist-info/METADATA
flasky_cli-1.0.3.dist-info/WHEEL
flasky_cli-1.0.3.dist-info/entry_points.txt
flasky_cli-1.0.3.dist-info/RECORD
